[ {
    "dislikes" : 0,
    "id" : 0,
    "likes" : 0,
    "lyricsurl": "https://firebasestorage.googleapis.com/v0/b/africariyoki.appspot.com/o/ifdavido.txt?alt=media&token=b5379ce4-4c88-4619-a6d2-f64a398bbf09",
    "plays" : 0,
    "singer" : "Chuck Berry",
    "audiourl": "https://firebasestorage.googleapis.com/v0/b/africariyoki.appspot.com/o/preview_accompaniment_Davido%20-%20If%20(Official%20Music%20Video).mp3?alt=media&token=5e3883ef-468f-470c-b4ae-e5a117152c51",
    "title" : "Johnny B. Goode"
  }, {
    "dislikes" : 0,
    "id" : 1,
    "likes" : 0,
    "lyricsurl": "https://firebasestorage.googleapis.com/v0/b/africariyoki.appspot.com/o/ifdavido.txt?alt=media&token=b5379ce4-4c88-4619-a6d2-f64a398bbf09",
    "plays" : 0,
    "singer" : "Elton John",
    "audiourl": "https://firebasestorage.googleapis.com/v0/b/africariyoki.appspot.com/o/preview_accompaniment_Davido%20-%20If%20(Official%20Music%20Video).mp3?alt=media&token=5e3883ef-468f-470c-b4ae-e5a117152c51",
    "title" : "Your Song"
  }, {
    "dislikes" : 0,
    "id" : 2,
    "likes" : 0,
    "lyricsurl": "https://firebasestorage.googleapis.com/v0/b/africariyoki.appspot.com/o/ifdavido.txt?alt=media&token=b5379ce4-4c88-4619-a6d2-f64a398bbf09",
    "plays" : 0,
    "singer" : "Journey",
    "audiourl": "https://firebasestorage.googleapis.com/v0/b/africariyoki.appspot.com/o/preview_accompaniment_Davido%20-%20If%20(Official%20Music%20Video).mp3?alt=media&token=5e3883ef-468f-470c-b4ae-e5a117152c51",
    "title" : "Don't Stop Believing"
  }, {
    "dislikes" : 0,
    "id" : 3,
    "likes" : 0,
    "lyricsurl": "https://firebasestorage.googleapis.com/v0/b/africariyoki.appspot.com/o/ifdavido.txt?alt=media&token=b5379ce4-4c88-4619-a6d2-f64a398bbf09",
    "plays" : 0,
    "singer" : "Eagles",
    "audiourl": "https://firebasestorage.googleapis.com/v0/b/africariyoki.appspot.com/o/preview_accompaniment_Davido%20-%20If%20(Official%20Music%20Video).mp3?alt=media&token=5e3883ef-468f-470c-b4ae-e5a117152c51",
    "title" : "Hotel California"
  }, {
    "dislikes" : 0,
    "id" : 4,
    "likes" : 0,
    "lyricsurl": "https://firebasestorage.googleapis.com/v0/b/africariyoki.appspot.com/o/ifdavido.txt?alt=media&token=b5379ce4-4c88-4619-a6d2-f64a398bbf09",
    "plays" : 0,
    "singer" : "Avril Lavigne",
    "audiourl": "https://firebasestorage.googleapis.com/v0/b/africariyoki.appspot.com/o/preview_accompaniment_Davido%20-%20If%20(Official%20Music%20Video).mp3?alt=media&token=5e3883ef-468f-470c-b4ae-e5a117152c51",
    "title" : "When You're Gone"
  }, {
    "dislikes" : 0,
    "id" : 5,
    "likes" : 0,
    "lyricsurl": "https://firebasestorage.googleapis.com/v0/b/africariyoki.appspot.com/o/ifdavido.txt?alt=media&token=b5379ce4-4c88-4619-a6d2-f64a398bbf09",
    "plays" : 0,
    "singer" : "Christina Aguilera",
    "audiourl": "https://firebasestorage.googleapis.com/v0/b/africariyoki.appspot.com/o/preview_accompaniment_Davido%20-%20If%20(Official%20Music%20Video).mp3?alt=media&token=5e3883ef-468f-470c-b4ae-e5a117152c51",
    "title" : "Reflection"
  }, {
    "dislikes" : 0,
    "id" : 6,
    "likes" : 0,
    "lyricsurl": "https://firebasestorage.googleapis.com/v0/b/africariyoki.appspot.com/o/ifdavido.txt?alt=media&token=b5379ce4-4c88-4619-a6d2-f64a398bbf09",
    "plays" : 0,
    "singer" : "Bruno Mars",
    "audiourl": "https://firebasestorage.googleapis.com/v0/b/africariyoki.appspot.com/o/preview_accompaniment_Davido%20-%20If%20(Official%20Music%20Video).mp3?alt=media&token=5e3883ef-468f-470c-b4ae-e5a117152c51",
    "title" : "Just The Way You Are"
  }, {
    "dislikes" : 0,
    "id" : 7,
    "likes" : 0,
    "lyricsurl": "https://firebasestorage.googleapis.com/v0/b/africariyoki.appspot.com/o/ifdavido.txt?alt=media&token=b5379ce4-4c88-4619-a6d2-f64a398bbf09",
    "plays" : 0,
    "singer" : "Josh Groban",
    "audiourl": "https://firebasestorage.googleapis.com/v0/b/africariyoki.appspot.com/o/preview_accompaniment_Davido%20-%20If%20(Official%20Music%20Video).mp3?alt=media&token=5e3883ef-468f-470c-b4ae-e5a117152c51",
    "title" : "You Raise Me Up"
  }, {
    "dislikes" : 0,
    "id" : 8,
    "likes" : 0,
    "lyricsurl": "https://firebasestorage.googleapis.com/v0/b/africariyoki.appspot.com/o/ifdavido.txt?alt=media&token=b5379ce4-4c88-4619-a6d2-f64a398bbf09",
    "plays" : 0,
    "singer" : "Westlife",
    "audiourl": "https://firebasestorage.googleapis.com/v0/b/africariyoki.appspot.com/o/preview_accompaniment_Davido%20-%20If%20(Official%20Music%20Video).mp3?alt=media&token=5e3883ef-468f-470c-b4ae-e5a117152c51",
    "title" : "My Love"
  }, {
    "dislikes" : 0,
    "id" : 9,
    "likes" : 0,
    "lyricsurl": "https://firebasestorage.googleapis.com/v0/b/africariyoki.appspot.com/o/ifdavido.txt?alt=media&token=b5379ce4-4c88-4619-a6d2-f64a398bbf09",
    "plays" : 0,
    "singer" : "Idina Menzel",
    "audiourl": "https://firebasestorage.googleapis.com/v0/b/africariyoki.appspot.com/o/preview_accompaniment_Davido%20-%20If%20(Official%20Music%20Video).mp3?alt=media&token=5e3883ef-468f-470c-b4ae-e5a117152c51",
    "title" : "Let It Go"
  }, {
    "dislikes" : 0,
    "id" : 10,
    "likes" : 0,
    "lyricsurl": "https://firebasestorage.googleapis.com/v0/b/africariyoki.appspot.com/o/ifdavido.txt?alt=media&token=b5379ce4-4c88-4619-a6d2-f64a398bbf09",
    "plays" : 0,
    "singer" : "Bruno Mars",
    "audiourl": "https://firebasestorage.googleapis.com/v0/b/africariyoki.appspot.com/o/preview_accompaniment_Davido%20-%20If%20(Official%20Music%20Video).mp3?alt=media&token=5e3883ef-468f-470c-b4ae-e5a117152c51",
    "title" : "The Lazy Song"
  }, {
    "dislikes" : 0,
    "id" : 11,
    "likes" : 0,
    "lyricsurl": "https://firebasestorage.googleapis.com/v0/b/africariyoki.appspot.com/o/ifdavido.txt?alt=media&token=b5379ce4-4c88-4619-a6d2-f64a398bbf09",
    "plays" : 0,
    "singer" : "Davido",
    "audiourl": "https://firebasestorage.googleapis.com/v0/b/africariyoki.appspot.com/o/preview_accompaniment_Davido%20-%20If%20(Official%20Music%20Video).mp3?alt=media&token=5e3883ef-468f-470c-b4ae-e5a117152c51",
    "title" : "Jowo"
  }, {
    "dislikes" : 0,
    "id" : 12,
    "likes" : 0,
    "lyricsurl": "https://firebasestorage.googleapis.com/v0/b/africariyoki.appspot.com/o/ifdavido.txt?alt=media&token=b5379ce4-4c88-4619-a6d2-f64a398bbf09",
    "plays" : 0,
    "singer" : "Davido",
    "audiourl": "https://firebasestorage.googleapis.com/v0/b/africariyoki.appspot.com/o/preview_accompaniment_Davido%20-%20If%20(Official%20Music%20Video).mp3?alt=media&token=5e3883ef-468f-470c-b4ae-e5a117152c51",
    "title" : "If"
  } ]
